README.md
setup.py
dellsc/clone_volume
dellsc/create_snapshot
dellsc/delete_volume
dellsc/record_recycled_volumes
dellsc/remove_recycled_volumes
dellsc/replace_volume
ucamdsm/__init__.py
ucamdsm/__main__.py
ucamdsm.egg-info/PKG-INFO
ucamdsm.egg-info/SOURCES.txt
ucamdsm.egg-info/dependency_links.txt
ucamdsm.egg-info/entry_points.txt
ucamdsm.egg-info/top_level.txt
ucamdsm/lib/__init__.py
ucamdsm/lib/connection.py
ucamdsm/lib/httpclient.py
ucamdsm/lib/options.py
ucamdsm/lib/process.py
ucamdsm/lib/task.py