Metadata-Version: 2.1
Name: ucamdsm
Version: 1.3.8
Summary: A Dell SC tasks automation using REST API
Home-page: https://gitlab.developers.cam.ac.uk/uis/infra/dell-sc
Author: UIS Infrastructure Servers and Storage, University of Cambridge
Author-email: wh330@cam.ac.uk
License: MIT License (MIT)
Platform: UNKNOWN
